{"药品": 27, "采购": 15, "医保": 14, "新药": 8, "目录": 8, "创新": 7, "纳入": 6, "创制": 5, "临床": 5, "药": 5, "平台": 5, "2020": 4, "国家": 4, "药物": 4, "挂网": 4, "谈判": 3, "科技": 3, "专项": 3, "急需": 3, "用药": 3, "需求": 3, "品种": 3, "质量": 3, "符合条件": 3, "支持": 3, "中": 3, "专利": 3, "调整": 3, "工作": 3, "国产": 3, "进一步": 3, "完善": 3, "省级": 3, "竞争": 3, "规范": 3, "国家医疗保障局": 2, "提案": 2, "答复": 2, "提出": 2, "成果": 2, "健康": 2, "实施": 2, "防治": 2, "疾病": 2, "余种": 2, "按程序": 2, "我国": 2, "分子": 2, "靶向": 2, "均": 2, "准入": 2, "国外": 2, "患者": 2, "按规定": 2, "申报": 2, "一步": 2, "支付": 2, "给予": 2, "意见": 2, "实行": 2, "供应": 2, "阳光": 2, "市场": 2, "带量": 2, "建立": 2, "招标": 2, "有序": 2, "规则": 2, "公平竞争": 2, "企业": 2, "政协": 1, "十三届": 1, "全国": 1, "委员会": 1, "第三次": 1, "会议": 1, "3778": 1, "财税": 1, "金融类": 1, "276": 1, "函": 1, "157": 1, "张洪春": 1, "委员": 1, "开启": 1, "绿色通道": 1, "收悉": 1, "现": 1, "卫生": 1, "委": 1, "牵头": 1, "组织": 1, "2008": 1, "着力": 1, "研制": 1, "应对": 1, "突发": 1, "更好": 1, "累计": 1, "153": 1, "证书": 1, "类": 1, "49": 1, "29": 1, "个化药": 1, "20": 1, "生物": 1, "化学": 1, "仿制": 1, "109": 1, "中药": 1, "34": 1, "生物制品": 1, "27": 1, "技术改造": 1, "200": 1, "提升": 1, "部门": 1, "始终": 1, "高度重视": 1, "2019": 1, "年版": 1, "数量": 1, "2709": 1, "绝大多数": 1, "原创": 1, "抗癌": 1, "西达": 1, "苯胺": 1, "全球": 1, "首个": 1, "治疗": 1, "晚期": 1, "胃癌": 1, "抗": 1, "血管": 1, "生成": 1, "阿帕替": 1, "尼": 1, "第一个": 1, "自主": 1, "知识产权": 1, "抗肿瘤": 1, "盐酸": 1, "埃克": 1, "替尼": 1, "PD": 1, "类药物": 1, "信迪利": 1, "单抗": 1, "上市": 1, "实体肿瘤": 1, "血液": 1, "肿瘤": 1, "领域": 1, "打破": 1, "垄断": 1, "促使": 1, "降价": 1, "大幅": 1, "减轻": 1, "负担": 1, "方案": 1, "形式": 1, "审查": 1, "约": 1, "700": 1, "不乏": 1, "医疗保险": 1, "管理": 1, "暂行办法": 1, "动态": 1, "调整机制": 1, "二": 1, "国务院办公厅": 1, "公立医院": 1, "指导": 1, "国办发": 1, "2015": 1, "联动": 1, "公开": 1, "透明": 1, "分类": 1, "全过程": 1, "综合": 1, "监管": 1, "切实": 1, "保障": 1, "医院": 1, "符合": 1, "条件": 1, "医疗机构": 1, "包括": 1, "在内": 1, "药均": 1, "保护": 1, "独占": 1, "期": 1, "创新性": 1, "有效性": 1, "回报": 1, "中共中央国务院": 1, "深化": 1, "医疗保障": 1, "制度": 1, "改革": 1, "招采": 1, "合一": 1, "量价": 1, "挂钩": 1, "医用": 1, "耗材": 1, "基础": 1, "交易": 1, "结算": 1, "监督": 1, "一体化": 1, "推进": 1, "构建": 1, "区域性": 1, "全国性": 1, "联盟": 1, "机制": 1, "价格合理": 1, "保障体系": 1, "操作": 1, "规范化": 1, "建设": 1, "统一": 1, "基本操作": 1, "流程": 1, "撤网": 1, "坚定不移": 1, "推动": 1, "优先": 1, "导向": 1, "应采": 1, "尽采": 1, "集采": 1, "覆盖": 1, "份额": 1, "金额": 1, "高": 1, "产品": 1, "营造": 1, "环境": 1, "引导": 1, "间": 1, "转化": 1, "产品质量": 1, "成本": 1, "高质量": 1, "发展": 1, "感谢您": 1, "事业": 1, "关心": 1, "11": 1}