{"服务": 24, "药事": 16, "收费": 13, "医疗": 8, "中": 8, "改革": 7, "公立医院": 6, "药学": 5, "药品": 5, "价格": 5, "患者": 5, "项目": 5, "政策": 4, "用药": 4, "方式": 4, "价值": 4, "服务项目": 4, "标准": 4, "提出": 3, "全面落实": 3, "服务费": 3, "实践": 3, "支持": 3, "补偿": 3, "机制": 3, "指导": 3, "取消": 3, "加成": 3, "医保": 3, "特定": 3, "人员": 3, "工作": 3, "国家医疗保障局": 2, "提案": 2, "答复": 2, "2019": 2, "科学": 2, "资源": 2, "作用": 2, "层面": 2, "缺乏": 2, "较大": 2, "鼓励": 2, "发展": 2, "国家": 2, "均": 2, "医疗机构": 2, "城市": 2, "综合": 2, "费用": 2, "规范": 2, "空间": 2, "同步": 2, "减少": 2, "调整": 2, "分摊": 2, "单独": 2, "设立": 2, "制定": 2, "服务体系": 2, "承受": 2, "总支出": 2, "合并": 2, "地区": 2, "政协": 1, "十三届": 1, "全国": 1, "委员会": 1, "第二次": 1, "会议": 1, "2343": 1, "体育类": 1, "231": 1, "函": 1, "126": 1, "陈": 1, "红专": 1, "位": 1, "委员": 1, "收悉": 1, "现": 1, "大众": 1, "健康": 1, "提高": 1, "效率": 1, "法律": 1, "清晰": 1, "统一": 1, "界定": 1, "差异": 1, "出发": 1, "结合实际": 1, "体现": 1, "公立": 1, "2015": 1, "国务院办公厅": 1, "印发": 1, "试点": 1, "意见": 1, "路径": 1, "建立": 1, "破除": 1, "药补": 1, "医": 1, "关键环节": 1, "降低": 1, "耗材": 1, "深化": 1, "支付": 1, "措施": 1, "留出": 1, "理顺": 1, "党中央": 1, "国务院": 1, "决策": 1, "部署": 1, "2017": 1, "合理收入": 1, "增加": 1, "财政投入": 1, "后药事": 1, "服务收入": 1, "平移": 1, "计入": 1, "化为": 1, "内部": 1, "收入": 1, "分配": 1, "二": 1, "现阶段": 1, "独立": 1, "确实": 1, "条件": 1, "制约": 1, "尚": 1, "支撑": 1, "努力": 1, "拓展": 1, "提供": 1, "更": 1, "总体": 1, "无论是": 1, "法律法规": 1, "行业标准": 1, "实际操作": 1, "尚未": 1, "明晰": 1, "考核": 1, "信息系统": 1, "电子": 1, "平台": 1, "前期": 1, "调研": 1, "过程": 1, "随机": 1, "访问": 1, "发放": 1, "处方": 1, "校对": 1, "简单": 1, "外": 1, "感受": 1, "不到": 1, "接受": 1, "此项": 1, "总量": 1, "控制": 1, "结构调整": 1, "医院": 1, "持续": 1, "负担": 1, "群众": 1, "一种": 1, "人头": 1, "被动": 1, "消费": 1, "量": 1, "面广": 1, "对全": 1, "社会": 1, "医药": 1, "影响": 1, "静脉": 1, "药物": 1, "配置": 1, "血药浓度": 1, "监测": 1, "现有": 1, "参与": 1, "会诊": 1, "法律依据": 1, "停留": 1, "概念": 1, "间接": 1, "大部分": 1, "省份": 1, "综合类": 1, "收取": 1, "建议": 1, "导向": 1, "经验": 1, "启发": 1, "意义": 1, "相关": 1, "专题研究": 1, "探索": 1, "适宜": 1, "收": 1, "付费": 1, "激励": 1, "浪费": 1, "发挥": 1, "感谢": 1, "医疗保障": 1, "关注": 1, "希望": 1, "一如既往": 1}