{"药品": 26, "医保": 22, "创新": 13, "谈判": 13, "目录": 13, "保障": 9, "支持": 7, "纳入": 6, "保": 6, "建立": 6, "企业": 6, "支付": 6, "制度": 6, "医疗保障": 6, "药": 5, "发展": 5, "国家": 5, "前提": 5, "新药": 5, "中": 5, "调整": 5, "工作": 5, "标准": 5, "评审": 4, "患者": 4, "群众": 4, "新": 4, "鼓励": 3, "公平": 3, "准入": 3, "优化": 3, "规则": 3, "上市": 3, "增长": 3, "销售": 3, "供应": 3, "尽力而为": 3, "量力而行": 3, "参保": 3, "目标": 3, "科学": 3, "客观": 3, "更好": 3, "人民": 3, "医疗": 3, "原则": 3, "体系": 3, "健康": 3, "2023": 2, "国家医疗保障局": 2, "全国": 2, "管理": 2, "提案": 2, "答复": 2, "提出": 2, "金融": 2, "监督管理": 2, "总局": 2, "医保局": 2, "定位": 2, "高质量": 2, "主体": 2, "续约": 2, "机制": 2, "预期": 2, "2022": 2, "新增": 2, "支出": 2, "亿元": 2, "提高": 2, "渠道": 2, "医院": 2, "零售": 2, "药店": 2, "政策": 2, "水平": 2, "提升": 2, "受益": 2, "基金": 2, "努力": 2, "价值": 2, "研究": 2, "我国": 2, "指标体系": 2, "主观": 2, "衡量": 2, "服务": 2, "疾病": 2, "金额": 2, "注重": 2, "普惠": 2, "市场化": 2, "测算": 2, "专家": 2, "完善": 2, "特定": 2, "市场": 2, "方": 2, "三": 2, "构建": 2, "多层次": 2, "持续": 2, "保险": 2, "保险公司": 2, "开发": 2, "医疗保险": 2, "产品": 2, "191": 1, "政协": 1, "十四届": 1, "委员会": 1, "第一次": 1, "会议": 1, "03483": 1, "社会": 1, "类": 1, "286": 1, "函": 1, "董小平": 1, "委员": 1, "市场准入": 1, "着手": 1, "源头": 1, "收悉": 1, "经商": 1, "现": 1, "始终": 1, "成立": 1, "公开": 1, "推动": 1, "医药行业": 1, "创新性": 1, "内容": 1, "稳定": 1, "年内": 1, "获批": 1, "108": 1, "竞价": 1, "105": 1, "2017": 1, "日后": 1, "占": 1, "比达": 1, "97%": 1, "惠民": 1, "为本": 1, "加快": 1, "节奏": 1, "等待时间": 1, "平均": 1, "近": 1, "缩短": 1, "不到": 1, "仅": 1, "半年": 1, "2019": 1, "59.49": 1, "481.89": 1, "7.1": 1, "倍": 1, "可及": 1, "性": 1, "建立健全": 1, "双通道": 1, "保障机制": 1, "两个": 1, "实行": 1, "报销": 1, "两年": 1, "15.5": 1, "万家": 1, "定点": 1, "缓解": 1, "进得": 1, "进不了": 1, "瓶颈": 1, "历次": 1, "把握": 1, "经济": 1, "财力": 1, "持续增长": 1, "基础": 1, "之上": 1, "脱离实际": 1, "超越阶段": 1, "保命钱": 1, "一分钱": 1, "花得": 1, "更值": 1, "购买": 1, "紧紧围绕": 1, "带来": 1, "价格水平": 1, "性价比": 1, "规范": 1, "评估": 1, "评价": 1, "推进": 1, "一套": 1, "符合": 1, "定性": 1, "定量": 1, "跨越": 1, "精准": 1, "赞同": 1, "总体": 1, "更": 1, "价格": 1, "疗效": 1, "促使": 1, "医药产业": 1, "走上": 1, "重": 1, "强": 1, "研发": 1, "道路": 1, "二": 1, "习近平": 1, "总书记": 1, "深刻": 1, "指出": 1, "全民": 1, "目的": 1, "解除": 1, "后顾之忧": 1, "应有": 1, "合适": 1, "适宜": 1, "程度": 1, "之外": 1, "过高": 1, "自付": 1, "降低": 1, "待遇": 1, "损害": 1, "能力": 1, "公平性": 1, "初衷": 1, "相": 1, "违背": 1, "以下几点": 1, "选择": 1, "发挥": 1, "作用": 1, "科学化": 1, "底价": 1, "环节": 1, "征求": 1, "意见": 1, "评分": 1, "走向": 1, "药物": 1, "经济学": 1, "科学性": 1, "报价": 1, "综合": 1, "环境": 1, "最终": 1, "成功": 1, "取决于": 1, "底线": 1, "交集": 1, "是从": 1, "情况": 1, "大部分": 1, "依托": 1, "世界": 1, "人口": 1, "最多": 1, "临床": 1, "认可": 1, "后均": 1, "销量": 1, "攀升": 1, "以价": 1, "换量": 1, "国际": 1, "经验": 1, "政府": 1, "共担": 1, "支": 1, "出": 1, "规律": 1, "内在": 1, "运行": 1, "认真落实": 1, "党中央": 1, "国务院": 1, "保险业": 1, "大力发展": 1, "商业": 1, "积极参与": 1, "建设": 1, "修订": 1, "办法": 1, "医疗器械": 1, "诊疗": 1, "方法": 1, "多样化": 1, "需求": 1, "团体": 1, "补充": 1, "百万": 1, "医疗险": 1, "防癌": 1, "险": 1, "外": 1, "费用": 1, "保险产品": 1, "治疗": 1, "提供": 1, "便利": 1, "一步": 1, "继续加强": 1, "相关": 1, "部门": 1, "沟通": 1, "顶层": 1, "设计": 1, "引导": 1, "调整机制": 1, "医药": 1, "感谢您": 1, "关心": 1, "10": 1, "31": 1}