{"起付线": 14, "医保": 14, "医疗": 11, "住院": 10, "支付": 10, "参保": 9, "费用": 8, "医疗保险": 8, "制度": 7, "贫困人口": 7, "水平": 7, "统筹": 7, "基金": 7, "医疗机构": 7, "政策": 7, "医疗保障": 6, "负担": 6, "大病": 6, "救助": 6, "标准": 6, "提高": 6, "居民": 6, "保险": 5, "起付": 5, "比例": 5, "元": 5, "群众": 4, "人员": 4, "困难群众": 4, "确保": 4, "保障": 4, "建议": 3, "2019": 3, "国家": 3, "国务院": 3, "精准": 3, "城乡居民": 3, "设定": 3, "限额": 3, "门诊": 3, "降低": 3, "进一步": 3, "住院费用": 3, "纳入": 3, "农村": 3, "建档立卡": 3, "国家医疗保障局": 2, "答复": 2, "提出": 2, "取消": 2, "党中央": 2, "全民": 2, "三重": 2, "综合": 2, "减轻": 2, "建立": 2, "城镇职工": 2, "发展": 2, "地区": 2, "原则": 2, "中": 2, "机制": 2, "经济": 2, "分级": 2, "更好": 2, "定点": 2, "承担": 2, "职工": 2, "收入": 2, "快速增长": 2, "能力": 2, "筹资": 2, "需求": 2, "情况": 2, "三级": 2, "元到": 2, "800": 2, "之间": 2, "400": 2, "二": 2, "加大": 2, "落实": 2, "对象": 2, "倾斜": 2, "统一": 2, "年度": 2, "50%": 2, "我国": 2, "改革": 2, "十三届": 1, "全国人大": 1, "二次": 1, "会议": 1, "8374": 1, "69": 1, "丁照民": 1, "谷凤杰": 1, "朱桂艳": 1, "刘丽岩": 1, "齐嵩宇": 1, "初建": 1, "美": 1, "代表": 1, "收悉": 1, "经商": 1, "卫生": 1, "健康": 1, "委": 1, "现": 1, "十分重视": 1, "完善": 1, "建设": 1, "出台": 1, "一系列": 1, "措施": 1, "缓解": 1, "体系": 1, "联动": 1, "发力": 1, "施策": 1, "梯次": 1, "国": 1, "发": 1, "1998": 1, "44": 1, "社会主义": 1, "初级阶段": 1, "生产力": 1, "相适应": 1, "以收定": 1, "支": 1, "收支平衡": 1, "设置": 1, "目的": 1, "分担": 1, "促使": 1, "资源": 1, "利用": 1, "运行": 1, "转": 1, "小病": 1, "大养": 1, "过度": 1, "一种": 1, "约束": 1, "有利于": 1, "诊疗": 1, "效益": 1, "发挥": 1, "共济": 1, "功能": 1, "实践": 1, "医疗费": 1, "发生": 1, "需先": 1, "门槛": 1, "平均工资": 1, "10%": 1, "二十余年": 1, "职工工资": 1, "未": 1, "调整": 1, "事实": 1, "处于": 1, "逐年": 1, "状态": 1, "区": 1, "层级": 1, "分档": 1, "甲等": 1, "1000": 1, "二级": 1, "500": 1, "一级": 1, "乡镇": 1, "卫生院": 1, "200": 1, "吉林省": 1, "城镇居民": 1, "方法": 1, "1100": 1, "总体": 1, "全国": 1, "平均水平": 1, "倾斜政策": 1, "财政投入": 1, "覆盖范围": 1, "应保": 1, "尽保": 1, "缴费": 1, "补贴": 1, "特困": 1, "城乡": 1, "低保": 1, "资助": 1, "全": 1, "覆盖": 1, "初步统计": 1, "率": 1, "99.8%": 1, "公平": 1, "普惠": 1, "加快": 1, "推进": 1, "整合": 1, "建立健全": 1, "参照": 1, "管理": 1, "重点": 1, "较重": 1, "多发病": 1, "慢性病": 1, "力度": 1, "普惠性": 1, "人均": 1, "支配": 1, "60%": 1, "实行": 1, "报销": 1, "百分点": 1, "封顶": 1, "线": 1, "增强": 1, "托底": 1, "自付": 1, "低于": 1, "70%": 1, "明确规定": 1, "按规定": 1, "转诊": 1, "贫困": 1, "患者": 1, "连续": 1, "计算": 1, "省域": 1, "就医": 1, "结算": 1, "执行": 1, "同等": 1, "整体": 1, "不高": 1, "有限": 1, "疾病": 1, "人群": 1, "数量": 1, "庞大": 1, "差距": 1, "优化": 1, "顶层": 1, "设计": 1, "较强": 1, "参考": 1, "意义": 1, "一步": 1, "决策": 1, "部署": 1, "深化": 1, "成果": 1, "惠及": 1, "感谢": 1, "工作": 1, "关心": 1, "支持": 1, "15": 1}