{"医保": 8, "目录": 7, "工作": 6, "2020": 5, "管理": 5, "调整": 5, "建议": 4, "药品": 4, "医疗保险": 3, "用药": 3, "暂行办法": 3, "征求意见": 3, "参保": 3, "医疗保障": 3, "完善": 3, "方案": 3, "国家医疗保障局": 2, "答复": 2, "稿": 2, "我局": 2, "企业": 2, "人员": 2, "研究": 2, "简称": 2, "办法": 2, "动态": 2, "调整机制": 2, "相关": 2, "公布": 2, "十三届": 1, "全国人大": 1, "三次": 1, "会议": 1, "5348": 1, "90": 1, "胡季强": 1, "代表": 1, "提出": 1, "修改": 1, "收悉": 1, "现": 1, "29": 1, "门户网站": 1, "公开": 1, "收到": 1, "医院": 1, "群体": 1, "数千条": 1, "仔细": 1, "吸收": 1, "各方": 1, "统筹": 1, "后于": 1, "30": 1, "印发": 1, "中共中央国务院": 1, "深化": 1, "制度": 1, "改革": 1, "意见": 1, "制定": 1, "支付": 1, "监督": 1, "作出": 1, "党中央": 1, "国务院": 1, "决策": 1, "部署": 1, "近期": 1, "启动": 1, "新一轮": 1, "国家": 1, "分为": 1, "申报": 1, "专家": 1, "评审": 1, "谈判": 1, "竞价": 1, "阶段": 1, "进展": 1, "顺利": 1, "预期": 1, "今年年底": 1, "前": 1, "一步": 1, "进一步": 1, "努力实现": 1, "动态化": 1, "常态": 1, "化": 1, "结构": 1, "优化": 1, "规范": 1, "资金": 1, "效益": 1, "更高": 1, "部门": 1, "协调": 1, "配合": 1, "诊疗": 1, "项目管理": 1, "需求": 1, "基金": 1, "筹资": 1, "能力": 1, "因素": 1, "做好": 1, "感谢您": 1, "事业": 1, "支持": 1, "关心": 1, "22": 1}