{"结算": 25, "跨省": 19, "就医": 18, "异地": 15, "门诊": 11, "费用": 10, "医保": 8, "服务": 7, "试点": 7, "国家": 7, "系统": 7, "2020": 6, "住院费用": 6, "亿元": 6, "基金": 6, "支付": 6, "工作": 5, "定点": 5, "累计": 5, "医疗": 5, "地区": 5, "完善": 4, "医保局": 4, "医疗机构": 4, "家": 4, "总费用": 4, "万元": 4, "进一步": 3, "推进": 3, "新": 3, "备案": 3, "上线": 3, "群众": 3, "月底": 3, "万人次": 3, "长三角": 3, "本级": 3, "参保": 3, "提供": 3, "国家医疗保障局": 2, "建议": 2, "答复": 2, "提出": 2, "加快": 2, "人民": 2, "数量": 2, "677": 2, "住院": 2, "2018": 2, "稳妥": 2, "试点工作": 2, "京津冀": 2, "西南": 2, "五": 2, "省区": 2, "三个": 2, "区域": 2, "全国": 2, "启动": 2, "覆盖": 2, "城市": 2, "2019": 2, "12": 2, "统筹": 2, "人员": 2, "个人账户": 2, "人次": 2, "正式": 2, "功能": 2, "支持": 2, "多种": 2, "十三届": 1, "全国人大": 1, "三次": 1, "会议": 1, "5674": 1, "15": 1, "刘": 1, "英才": 1, "代表": 1, "收悉": 1, "现": 1, "党中央": 1, "国务院": 1, "高度重视": 1, "党": 1, "十九": 1, "届": 1, "四中全会": 1, "明确要求": 1, "制度": 1, "政府": 1, "报告": 1, "明确提出": 1, "中心": 1, "发展": 1, "思想": 1, "手续": 1, "繁琐": 1, "跑腿": 1, "报销": 1, "难": 1, "垫支": 1, "负担重": 1, "堵点": 1, "难点": 1, "开发": 1, "统一": 1, "不断完善": 1, "政策": 1, "简化": 1, "流程": 1, "优化": 1, "需求": 1, "35008": 1, "平台": 1, "万人": 1, "562": 1, "总": 1, "1353.7": 1, "799.6": 1, "比例": 1, "59.1%": 1, "便捷": 1, "做好": 1, "基础": 1, "155.5": 1, "3.8": 1, "2.2": 1, "率先": 1, "41": 1, "已达": 1, "6759": 1, "153.5": 1, "3.7": 1, "2.1": 1, "重庆市": 1, "四川省": 1, "云南省": 1, "17": 1, "城镇职工": 1, "贵州省": 1, "铁路": 1, "电力系统": 1, "开通": 1, "1784": 1, "零售": 1, "药店": 1, "购药": 1, "18224": 1, "367.8": 1, "362.4": 1, "1140": 1, "29.9": 1, "9.8": 1, "有序": 1, "月初": 1, "运行": 1, "高效": 1, "稳定": 1, "技术支持": 1, "身份证": 1, "电子": 1, "凭证": 1, "介质": 1, "微信": 1, "程序": 1, "APP": 1, "协同": 1, "信息": 1, "共享": 1, "消息": 1, "快速": 1, "传递": 1, "实时": 1, "跟踪": 1, "一步": 1, "管理": 1, "稳步": 1, "省份": 1, "联网": 1, "2021": 1, "年底": 1, "更": 1, "方便快捷": 1, "一体化": 1, "感谢您": 1, "关心": 1}