{"罕见": 23, "医保": 18, "病": 15, "保障": 10, "病患者": 8, "费用": 7, "纳入": 7, "医疗保障": 7, "目录": 7, "支付": 7, "保险": 7, "医疗": 7, "用药": 6, "医疗保险": 6, "国家": 6, "药品": 6, "政策": 6, "建立": 5, "水平": 5, "救助": 5, "治疗": 4, "基金": 4, "比例": 4, "参保": 4, "健康": 4, "部门": 3, "药物": 3, "2019": 3, "患者": 3, "城乡居民": 3, "收入": 3, "提高": 3, "提供": 3, "筹资": 3, "多层次": 3, "商业": 3, "体系": 3, "疾病": 3, "国家医疗保障局": 2, "提案": 2, "答复": 2, "2020": 2, "提出": 2, "制度": 2, "调整": 2, "中": 2, "包括": 2, "坦片": 2, "价格": 2, "特别": 2, "昂贵": 2, "承受能力": 2, "职工": 2, "住院费用": 2, "70%": 2, "限额": 2, "支配": 2, "大病": 2, "50%": 2, "人均": 2, "贫困人口": 2, "承担": 2, "进一步": 2, "对象": 2, "解决": 2, "渠道": 2, "商业保险": 2, "支持": 2, "开发": 2, "保险产品": 2, "产品": 2, "政协": 1, "十三届": 1, "全国": 1, "委员会": 1, "第三次": 1, "会议": 1, "4221": 1, "社会": 1, "管理": 1, "类": 1, "361": 1, "函": 1, "201": 1, "熊": 1, "水龙": 1, "委员": 1, "收悉": 1, "经商": 1, "中国": 1, "银": 1, "保监会": 1, "现": 1, "机制": 1, "高度重视": 1, "工作": 1, "层面": 1, "发布": 1, "版": 1, "数量": 1, "1535": 1, "增加": 1, "2709": 1, "不断扩大": 1, "结构": 1, "优化": 1, "重组": 1, "凝血因子": 1, "利鲁唑": 1, "对症": 1, "过程": 1, "新增": 1, "儿童": 1, "原发性": 1, "肉碱": 1, "缺乏症": 1, "左卡尼汀": 1, "口服": 1, "溶液": 1, "准入": 1, "谈判": 1, "多发性": 1, "硬化症": 1, "特立": 1, "氟胺片": 1, "C": 1, "型尼曼": 1, "匹克病": 1, "麦格司": 1, "胶囊": 1, "肺动脉": 1, "高压": 1, "司来": 1, "帕": 1, "格片": 1, "波生": 1, "马昔腾": 1, "利奥": 1, "西呱片": 1, "10": 1, "余个": 1, "下降": 1, "提升": 1, "远超": 1, "原因": 1, "待遇": 1, "报销": 1, "80%": 1, "统筹": 1, "平均工资": 1, "居民": 1, "倍": 1, "覆盖": 1, "人群": 1, "达": 1, "起付线": 1, "降为": 1, "上年": 1, "60%": 1, "实行": 1, "倾斜": 1, "资助": 1, "在内": 1, "困难群众": 1, "参加": 1, "家庭": 1, "难以": 1, "给予": 1, "补助": 1, "降低": 1, "负担": 1, "原则上": 1, "低保": 1, "特困": 1, "人员": 1, "农村": 1, "建档立卡": 1, "年度": 1, "约": 1, "符合条件": 1, "贫困": 1, "仅": 1, "800": 1, "元": 1, "难以承受": 1, "多方": 1, "专项": 1, "方案": 1, "建议": 1, "现行制度": 1, "医药": 1, "情况": 1, "政府": 1, "主导": 1, "专项基金": 1, "需": 1, "慎重考虑": 1, "中共中央国务院": 1, "深化": 1, "改革": 1, "意见": 1, "医保局": 1, "会同": 1, "探索": 1, "措施": 1, "尽力而为": 1, "量力而行": 1, "逐步提高": 1, "二": 1, "引入": 1, "保障体系": 1, "保险业": 1, "大力发展": 1, "积极参与": 1, "建设": 1, "鼓励": 1, "保险机构": 1, "相关": 1, "完善": 1, "160": 1, "多家": 1, "保险公司": 1, "保险业务": 1, "涵盖": 1, "护理": 1, "失能": 1, "损失": 1, "意外保险": 1, "大类": 1, "超过": 1, "5000": 1, "已有": 1, "200": 1, "多种": 1, "之中": 1, "就医": 1, "一步": 1, "立足": 1, "保": 1, "定位": 1, "需求": 1, "能力": 1, "因素": 1, "专家": 1, "评审": 1, "疗效": 1, "确切": 1, "此基础": 1, "健全": 1, "推动": 1, "发展": 1, "充分发挥": 1, "风险管理": 1, "功能": 1, "作用": 1, "感谢您": 1, "事业": 1, "关心": 1, "12": 1}