{"罕见": 41, "病": 32, "医保": 17, "目录": 12, "药品": 9, "用药": 8, "保障": 8, "病患者": 8, "筛查": 8, "国家": 7, "健康": 7, "纳入": 7, "支付": 7, "政策": 7, "诊疗": 7, "医疗保障": 6, "医疗": 6, "救助": 6, "协作网": 6, "卫生": 5, "建立": 5, "部门": 5, "2019": 5, "水平": 5, "基金": 5, "参保": 5, "我国": 5, "相关": 5, "医院": 5, "委": 4, "治疗": 4, "患者": 4, "比例": 4, "提高": 4, "进一步": 4, "全国": 4, "早": 4, "建议": 3, "医疗保险": 3, "制度": 3, "工作": 3, "发布": 3, "包括": 3, "药物": 3, "城乡居民": 3, "保险": 3, "费用": 3, "提供": 3, "研究": 3, "一步": 3, "作用": 3, "规范": 3, "临床": 3, "疾病": 3, "新生儿": 3, "出生": 3, "缺陷": 3, "国家医疗保障局": 2, "答复": 2, "2020": 2, "提出": 2, "体系": 2, "红十字会": 2, "调整": 2, "中": 2, "儿童": 2, "坦片": 2, "价格": 2, "特别": 2, "昂贵": 2, "承受能力": 2, "职工": 2, "住院费用": 2, "70%": 2, "限额": 2, "支配": 2, "收入": 2, "大病": 2, "覆盖": 2, "人群": 2, "50%": 2, "人均": 2, "贫困人口": 2, "资助": 2, "在内": 2, "家庭": 2, "承担": 2, "补助": 2, "对象": 2, "人员": 2, "贫困": 2, "筹资": 2, "专项基金": 2, "需求": 2, "能力": 2, "健全": 2, "多层次": 2, "推动": 2, "更好": 2, "权益": 2, "诊治": 2, "印发": 2, "指南": 2, "信息": 2, "供应": 2, "做好": 2, "起到": 2, "预防": 2, "产前": 2, "产前诊断": 2, "常见": 2, "畸形": 2, "基因": 2, "十三届": 1, "全国人大": 1, "三次": 1, "会议": 1, "1352": 1, "191": 1, "雷冬竹": 1, "代表": 1, "加快": 1, "推进": 1, "建设": 1, "收悉": 1, "经商": 1, "银": 1, "保监会": 1, "现": 1, "高度重视": 1, "层面": 1, "版": 1, "数量": 1, "1535": 1, "增加": 1, "2709": 1, "不断扩大": 1, "结构": 1, "优化": 1, "重组": 1, "凝血因子": 1, "利鲁唑": 1, "对症": 1, "过程": 1, "新增": 1, "原发性": 1, "肉碱": 1, "缺乏症": 1, "左卡尼汀": 1, "口服": 1, "溶液": 1, "准入": 1, "谈判": 1, "多发性": 1, "硬化症": 1, "特立": 1, "氟胺片": 1, "C": 1, "型尼曼": 1, "匹克病": 1, "麦格司": 1, "胶囊": 1, "肺动脉": 1, "高压": 1, "司来": 1, "帕": 1, "格片": 1, "波生": 1, "马昔腾": 1, "利奥": 1, "西呱片": 1, "10": 1, "余个": 1, "下降": 1, "提升": 1, "远超": 1, "原因": 1, "待遇": 1, "报销": 1, "80%": 1, "统筹": 1, "平均工资": 1, "居民": 1, "倍": 1, "达": 1, "起付线": 1, "降为": 1, "上年": 1, "60%": 1, "实行": 1, "倾斜": 1, "困难群众": 1, "参加": 1, "难以": 1, "给予": 1, "降低": 1, "负担": 1, "原则上": 1, "低保": 1, "特困": 1, "农村": 1, "建档立卡": 1, "年度": 1, "约": 1, "符合条件": 1, "解决": 1, "渠道": 1, "仅": 1, "800": 1, "元": 1, "难以承受": 1, "社会": 1, "组织": 1, "某种": 1, "特定": 1, "专项": 1, "慈善": 1, "活动": 1, "设立": 1, "首个": 1, "14": 1, "周岁": 1, "重型": 1, "再生": 1, "障碍": 1, "贫血": 1, "东方": 1, "天使": 1, "共": 1, "患儿": 1, "近": 1, "300": 1, "总额": 1, "700": 1, "余万元": 1, "立足": 1, "保": 1, "定位": 1, "因素": 1, "专家": 1, "评审": 1, "疗效": 1, "确切": 1, "此基础": 1, "发展": 1, "商业": 1, "充分发挥": 1, "商业保险": 1, "风险管理": 1, "功能": 1, "中共中央国务院": 1, "深化": 1, "改革": 1, "意见": 1, "措施": 1, "二": 1, "管理": 1, "联合": 1, "科技部": 1, "工业": 1, "信息化": 1, "部": 1, "国家药品监督管理局": 1, "五": 1, "第一批": 1, "制定": 1, "参考": 1, "卫健委": 1, "制订": 1, "程序": 1, "更新": 1, "病历": 1, "登记": 1, "完善": 1, "服务体系": 1, "医务人员": 1, "规范化": 1, "通知": 1, "国卫办": 1, "医函": 1, "157": 1, "先行": 1, "遴选": 1, "324": 1, "家": 1, "处方": 1, "集": 1, "监测": 1, "短缺": 1, "预警": 1, "报告": 1, "努力": 1, "衔接": 1, "院际": 1, "调剂": 1, "配送": 1, "物流": 1, "延伸": 1, "方式": 1, "就近": 1, "取药": 1, "网络": 1, "中心": 1, "省级": 1, "全": 1, "配合": 1, "服务": 1, "合法权益": 1, "三": 1, "已有": 1, "染色体": 1, "开放性": 1, "神经管": 1, "超声": 1, "胎儿": 1, "尚未": 1, "常规": 1, "省市": 1, "病种": 1, "省内": 1, "重点": 1, "民生": 1, "项目": 1, "风险": 1, "高危": 1, "产": 1, "前": 1, "检测": 1, "地方": 1, "经验": 1, "技术": 1, "流程": 1, "探索": 1, "病高危": 1, "发现": 1, "诊断": 1, "干预": 1, "感谢您": 1, "事业": 1, "支持": 1, "12": 1}